{
  "po" : 
  {
    "en_US" : 
    {
      "branch" : "",
      "commit" : 
      {
        "date" : "",
        "hash" : "",
        "title" : ""
      }
    },
    "zh_CN" : 
    {
      "branch" : "main",
      "commit" : 
      {
        "date" : "2026-01-23 14:57:31 +0000",
        "hash" : "d222ddc4d90743dfc1e53b610be8fc9d95893d2c",
        "title" : "Auto merge of #151501 - flip1995:clippy-subtree-update, r=Manishearth"
      }
    },
    "zh_TW" : 
    {
      "branch" : "main",
      "commit" : 
      {
        "date" : "2026-01-23 14:57:31 +0000",
        "hash" : "d222ddc4d90743dfc1e53b610be8fc9d95893d2c",
        "title" : "Auto merge of #151501 - flip1995:clippy-subtree-update, r=Manishearth"
      }
    }
  },
  "pot" : 
  {
    "branch" : "main",
    "commit" : 
    {
      "date" : "2026-02-17 02:03:25 +0000",
      "hash" : "d1a11b670b617f1370f7b1cdf86e225a4e070f15",
      "title" : "Auto merge of #152739 - Zalathar:rollup-8qaJ8F2, r=Zalathar"
    }
  },
  "type" : "branch",
  "version" : "nightly"
}